pingtunnel/Controller.py
pingtunnel/__init__.py
pingtunnel/__main__.py
pingtunnel-1.1.0.dist-info/LICENSE.md
pingtunnel-1.1.0.dist-info/METADATA
pingtunnel-1.1.0.dist-info/WHEEL
pingtunnel-1.1.0.dist-info/entry_points.txt
pingtunnel-1.1.0.dist-info/top_level.txt
pingtunnel-1.1.0.dist-info/RECORD
