Metadata-Version: 2.1
Name: pingtunnel
Version: 1.1.0
Summary: Test possible data exfiltration through ping requests
Home-page: https://github.com/5f0ne/pingtunnel
Author: 5f0
License: MIT
Classifier: Operating System :: OS Independent 
Classifier: Programming Language :: Python :: 3 
Classifier: License :: OSI Approved :: MIT License 
License-File: LICENSE.md
Requires-Dist: icmplib
